screenshot2code/__init__.py
screenshot2code/hello.py
screenshot2code-0.0.1.dist-info/METADATA
screenshot2code-0.0.1.dist-info/WHEEL
screenshot2code-0.0.1.dist-info/top_level.txt
screenshot2code-0.0.1.dist-info/RECORD
